<?xml version="1.0" encoding="utf-8"?>
<yaml xmlns:yamlconv="yamlconv" yamlconv:endianness="big" yamlconv:offsetCount="3">
  <Objs type="array">
    <value HashId="1978784192" SRTHash="-397558048">
      <_Parameters SharpWeaponJudgeType="0">
        <DropTable type="string">Normal</DropTable>
      </_Parameters>
      <Rotate type="array">
        <value>1.570796f</value>
        <value>0f</value>
        <value>0f</value>
      </Rotate>
      <Translate type="array">
        <value>0f</value>
        <value>0f</value>
        <value>0f</value>
      </Translate>
      <UnitConfigName type="string">DgnObj_DLC_IbutsuExD_WallSpike_A_01</UnitConfigName>
    </value>
    <value HashId="-223487551" SRTHash="35114508">
      <Rotate type="array">
        <value>1.570796f</value>
        <value>0f</value>
        <value>0f</value>
      </Rotate>
      <Translate type="array">
        <value>0f</value>
        <value>0f</value>
        <value>0f</value>
      </Translate>
      <UnitConfigName type="string">DgnObj_DLC_IbutsuExD_Cylinder_A_01</UnitConfigName>
    </value>
  </Objs>
  <Rails type="array" />
</yaml>